Workbook

Sheet Read Me
A1: Manual Benchmark Workbook — Earned Value Management
A4: Project Academic Block (G+4 RCC) - Institutional Campus
A5: Code CE725-CASE-01
A6: BAC Rs 140,000,000.00
A7: Baseline 12 monthly periods
A8: Data date end of Period 6 (Sep-2026)
A9: Benchmark reporting periods 5 and 6
A11: PURPOSE
A13: This workbook is the independent manual benchmark for the EVM dashboard.
A14: Every earned value figure in it is produced by a typed Excel formula acting
A15: on the raw inputs on the 'Inputs' and 'Baseline' sheets. Click any green cell
A16: to see the arithmetic. No value here is copied from the Python tool.
... A48: Excel evaluates them.

Sheet Inputs
A1: Raw Inputs
A2: Hand-entered data. Every other number in this workbook is derived from these cells.
A4: WBS ID | B4: Work Package | C4: Budget (Rs) | D4: AC P1 | E4: AC P2 | F4: AC P3 | G4: AC P4 | H4: AC P5 | I4: AC P6 | J4: %C P1 | K4: %C P2 | L4: %C P3 | M4: %C P4 | N4: %C P5 | O4: %C P6
A5: 1.1 | B5: Site mobilisation and enabling works | C5: 2500000 | D5: 1500000 | E5: 1200000 | F5: 0 | G5: 0 | H5: 0 | I5: 0 | J5: 0.55 | K5: 1 | L5: 1 | M5: 1 | N5: 1 | O5: 1
A6: 1.2 | B6: Site office, stores and labour accommodation | C6: 1800000 | D6: 950000 | E6: 900000 | F6: 0 | G6: 0 | H6: 0 | I6: 0 | J6: 0.5 | K6: 1 | L6: 1 | M6: 1 | N6: 1 | O6: 1
A7: 2.1 | B7: Excavation and earthwork | C7: 4200000 | D7: 1100000 | E7: 1500000 | F7: 1650000 | G7: 1100000 | H7: 750000 | I7: 0 | J7: 0.2 | K7: 0.45 | L7: 0.72 | M7: 0.9 | N7: 1 | O7: 1
A8: 2.2 | B8: PCC and footings | C8: 6800000 | D8: 0 | E8: 1100000 | F8: 1950000 | G8: 2500000 | H8: 1850000 | I8: 0 | J8: 0 | K8: 0.15 | L8: 0.42 | M8: 0.78 | N8: 1 | O8: 1
A9: 2.3 | B9: Foundation RCC up to plinth | C9: 9500000 | D9: 0 | E9: 0 | F9: 1900000 | G9: 3000000 | H9: 3400000 | I9: 2500000 | J9: 0 | K9: 0 | L9: 0.18 | M9: 0.46 | N9: 0.8 | O9: 1
A10: 2.4 | B10: Plinth beams and backfilling | C10: 3800000 | D10: 0 | E10: 0 | F10: 0 | G10: 850000 | H10: 1600000 | I10: 1650000 | J10: 0 | K10: 0 | L10: 0 | M10: 0.2 | N10: 0.62 | O10: 1
A11: 3.1 | B11: RCC columns, ground to fourth floor | C11: 14500000 | D11: 0 | E11: 0 | F11: 0 | G11: 0 | H11: 1300000 | I11: 2300000 | J11: 0 | K11: 0 | L11: 0 | M11: 0 | N11: 0.08 | O11: 0.22
A12: 3.2 | B12: RCC beams and slabs, ground to fourth floor | C12: 21000000 | D12: 0 | E12: 0 | F12: 0 | G12: 0 | H12: 1200000 | I12: 2100000 | J12: 0 | K12: 0 | L12: 0 | M12: 0 | N12: 0.05 | O12: 0.14
A13: 3.3 | B13: Staircase and lift core RCC | C13: 5500000 | D13: 0 | E13: 0 | F13: 0 | G13: 0 | H13: 0 | I13: 0 | J13: 0 | K13: 0 | L13: 0 | M13: 0 | N13: 0 | O13: 0
A14: 4.1 | B14: Block masonry | C14: 8800000 | D14: 0 | E14: 0 | F14: 0 | G14: 0 | H14: 0 | I14: 0 | J14: 0 | K14: 0 | L14: 0 | M14: 0 | N14: 0 | O14: 0
A15: 4.2 | B15: Internal plaster | C15: 5200000 | D15: 0 | E15: 0 | F15: 0 | G15: 0 | H15: 0 | I15: 0 | J15: 0 | K15: 0 | L15: 0 | M15: 0 | N15: 0 | O15: 0
A16: 4.3 | B16: External plaster and texture finish | C16: 4600000 | D16: 0 | E16: 0 | F16: 0 | G16: 0 | H16: 0 | I16: 0 | J16: 0 | K16: 0 | L16: 0 | M16: 0 | N16: 0 | O16: 0
... A23: 6.2 | B23: Testing, commissioning and handover | C23: 2800000 | D23: 0 | E23: 0 | F23: 0 | G23: 0 | H23: 0 | I23: 0 | J23: 0 | K23: 0 | L23: 0 | M23: 0 | N23: 0 | O23: 0
B24: TOTAL | C24: =SUM(C5:C23) | D24: =SUM(D5:D23) | E24: =SUM(E5:E23) | F24: =SUM(F5:F23) | G24: =SUM(G5:G23) | H24: =SUM(H5:H23) | I24: =SUM(I5:I23)
B26: BAC (sum of work package budgets) | C26: =C24

Sheet Baseline
A1: Time-Phased Budget (Planned Value)
A2: Planned value per work package per baseline period. Row 'Cumulative PV' is the S-curve.
A4: WBS ID | B4: Work Package | C4: PV P1 | D4: PV P2 | E4: PV P3 | F4: PV P4 | G4: PV P5 | H4: PV P6 | I4: PV P7 | J4: PV P8 | K4: PV P9 | L4: PV P10 | M4: PV P11 | N4: PV P12 | O4: Row total | P4: Budget check
A5: 1.1 | B5: Site mobilisation and enabling works | C5: 1250000 | D5: 1250000 | E5: 0 | F5: 0 | G5: 0 | H5: 0 | I5: 0 | J5: 0 | K5: 0 | L5: 0 | M5: 0 | N5: 0 | O5: =SUM(C5:N5) | P5: =IF(ROUND(O5-Inputs!C5,2)=0,"OK","MISMATCH")
A6: 1.2 | B6: Site office, stores and labour accommodation | C6: 900000 | D6: 900000 | E6: 0 | F6: 0 | G6: 0 | H6: 0 | I6: 0 | J6: 0 | K6: 0 | L6: 0 | M6: 0 | N6: 0 | O6: =SUM(C6:N6) | P6: =IF(ROUND(O6-Inputs!C6,2)=0,"OK","MISMATCH")
A7: 2.1 | B7: Excavation and earthwork | C7: 1400000 | D7: 1400000 | E7: 1400000 | F7: 0 | G7: 0 | H7: 0 | I7: 0 | J7: 0 | K7: 0 | L7: 0 | M7: 0 | N7: 0 | O7: =SUM(C7:N7) | P7: =IF(ROUND(O7-Inputs!C7,2)=0,"OK","MISMATCH")
A8: 2.2 | B8: PCC and footings | C8: 0 | D8: 1762963 | E8: 3274074.1 | F8: 1762963 | G8: 0 | H8: 0 | I8: 0 | J8: 0 | K8: 0 | L8: 0 | M8: 0 | N8: 0 | O8: =SUM(C8:N8) | P8: =IF(ROUND(O8-Inputs!C8,2)=0,"OK","MISMATCH")
A9: 2.3 | B9: Foundation RCC up to plinth | C9: 0 | D9: 0 | E9: 2462963 | F9: 4574074.1 | G9: 2462963 | H9: 0 | I9: 0 | J9: 0 | K9: 0 | L9: 0 | M9: 0 | N9: 0 | O9: =SUM(C9:N9) | P9: =IF(ROUND(O9-Inputs!C9,2)=0,"OK","MISMATCH")
A10: 2.4 | B10: Plinth beams and backfilling | C10: 0 | D10: 0 | E10: 0 | F10: 1900000 | G10: 1900000 | H10: 0 | I10: 0 | J10: 0 | K10: 0 | L10: 0 | M10: 0 | N10: 0 | O10: =SUM(C10:N10) | P10: =IF(ROUND(O10-Inputs!C10,2)=0,"OK","MISMATCH")
A11: 3.1 | B11: RCC columns, ground to fourth floor | C11: 0 | D11: 0 | E11: 0 | F11: 0 | G11: 1508000 | H11: 3596000 | I11: 4292000 | J11: 3596000 | K11: 1508000 | L11: 0 | M11: 0 | N11: 0 | O11: =SUM(C11:N11) | P11: =IF(ROUND(O11-Inputs!C11,2)=0,"OK","MISMATCH")
A12: 3.2 | B12: RCC beams and slabs, ground to fourth floor | C12: 0 | D12: 0 | E12: 0 | F12: 0 | G12: 1555555.6 | H12: 3888888.9 | I12: 5055555.6 | J12: 5055555.6 | K12: 3888888.9 | L12: 1555555.6 | M12: 0 | N12: 0 | O12: =SUM(C12:N12) | P12: =IF(ROUND(O12-Inputs!C12,2)=0,"OK","MISMATCH")
A13: 3.3 | B13: Staircase and lift core RCC | C13: 0 | D13: 0 | E13: 0 | F13: 0 | G13: 0 | H13: 1100000 | I13: 1100000 | J13: 1100000 | K13: 1100000 | L13: 1100000 | M13: 0 | N13: 0 | O13: =SUM(C13:N13) | P13: =IF(ROUND(O13-Inputs!C13,2)=0,"OK","MISMATCH")
A14: 4.1 | B14: Block masonry | C14: 0 | D14: 0 | E14: 0 | F14: 0 | G14: 0 | H14: 0 | I14: 915200 | J14: 2182400 | K14: 2604800 | L14: 2182400 | M14: 915200 | N14: 0 | O14: =SUM(C14:N14) | P14: =IF(ROUND(O14-Inputs!C14,2)=0,"OK","MISMATCH")
A15: 4.2 | B15: Internal plaster | C15: 0 | D15: 0 | E15: 0 | F15: 0 | G15: 0 | H15: 0 | I15: 0 | J15: 0 | K15: 812500 | L15: 1787500 | M15: 1787500 | N15: 812500 | O15: =SUM(C15:N15) | P15: =IF(ROUND(O15-Inputs!C15,2)=0,"OK","MISMATCH")
A16: 4.3 | B16: External plaster and texture finish | C16: 0 | D16: 0 | E16: 0 | F16: 0 | G16: 0 | H16: 0 | I16: 0 | J16: 0 | K16: 1150000 | L16: 1150000 | M16: 1150000 | N16: 1150000 | O16: =SUM(C16:N16) | P16: =IF(ROUND(O16-Inputs!C16,2)=0,"OK","MISMATCH")
... A23: 6.2 | B23: Testing, commissioning and handover | C23: 0 | D23: 0 | E23: 0 | F23: 0 | G23: 0 | H23: 0 | I23: 0 | J23: 0 | K23: 0 | L23: 0 | M23: 0 | N23: 2800000 | O23: =SUM(C23:N23) | P23: =IF(ROUND(O23-Inputs!C23,2)=0,"OK","MISMATCH")
B24: TOTAL | C24: =SUM(C5:C23) | D24: =SUM(D5:D23) | E24: =SUM(E5:E23) | F24: =SUM(F5:F23) | G24: =SUM(G5:G23) | H24: =SUM(H5:H23) | I24: =SUM(I5:I23) | J24: =SUM(J5:J23) | ... O24: =SUM(O5:O23)
B26: Cumulative PV (S-curve) | C26: =C24 | D26: =C26+D24 | E26: =D26+E24 | F26: =E26+F24 | G26: =F26+G24 | H26: =G26+H24 | I26: =H26+I24 | J26: =I26+J24 | K26: =J26+K24 | ... N26: =M26+N24
B28: The final cumulative value must equal BAC exactly. | O28: =IF(ROUND(M26-Inputs!C24,2)=0,"OK","MISMATCH")

Sheet Calc P5
A1: Earned Value by Work Package — end of Period 5 (Aug-2026)
A2: EV = cumulative percent complete x budget. PV and AC are cumulative to this period.
A4: WBS ID | B4: Work Package | C4: Budget (Rs) | D4: % Complete | E4: EV (Rs) | F4: PV cum (Rs) | G4: AC cum (Rs) | H4: CV (Rs) | I4: SV (Rs) | J4: CPI | K4: SPI
A5: 1.1 | B5: Site mobilisation and enabling works | C5: =Inputs!C5 | D5: =Inputs!N5 | E5: =C5*D5 | F5: =SUM(Baseline!C5:G5) | G5: =SUM(Inputs!D5:H5) | H5: =E5-G5 | I5: =E5-F5 | J5: =IF(G5=0,"",E5/G5) | K5: =IF(F5=0,"",E5/F5)
A6: 1.2 | B6: Site office, stores and labour accommodation | C6: =Inputs!C6 | D6: =Inputs!N6 | E6: =C6*D6 | F6: =SUM(Baseline!C6:G6) | G6: =SUM(Inputs!D6:H6) | H6: =E6-G6 | I6: =E6-F6 | J6: =IF(G6=0,"",E6/G6) | K6: =IF(F6=0,"",E6/F6)
A7: 2.1 | B7: Excavation and earthwork | C7: =Inputs!C7 | D7: =Inputs!N7 | E7: =C7*D7 | F7: =SUM(Baseline!C7:G7) | G7: =SUM(Inputs!D7:H7) | H7: =E7-G7 | I7: =E7-F7 | J7: =IF(G7=0,"",E7/G7) | K7: =IF(F7=0,"",E7/F7)
A8: 2.2 | B8: PCC and footings | C8: =Inputs!C8 | D8: =Inputs!N8 | E8: =C8*D8 | F8: =SUM(Baseline!C8:G8) | G8: =SUM(Inputs!D8:H8) | H8: =E8-G8 | I8: =E8-F8 | J8: =IF(G8=0,"",E8/G8) | K8: =IF(F8=0,"",E8/F8)
A9: 2.3 | B9: Foundation RCC up to plinth | C9: =Inputs!C9 | D9: =Inputs!N9 | E9: =C9*D9 | F9: =SUM(Baseline!C9:G9) | G9: =SUM(Inputs!D9:H9) | H9: =E9-G9 | I9: =E9-F9 | J9: =IF(G9=0,"",E9/G9) | K9: =IF(F9=0,"",E9/F9)
A10: 2.4 | B10: Plinth beams and backfilling | C10: =Inputs!C10 | D10: =Inputs!N10 | E10: =C10*D10 | F10: =SUM(Baseline!C10:G10) | G10: =SUM(Inputs!D10:H10) | H10: =E10-G10 | I10: =E10-F10 | J10: =IF(G10=0,"",E10/G10) | K10: =IF(F10=0,"",E10/F10)
A11: 3.1 | B11: RCC columns, ground to fourth floor | C11: =Inputs!C11 | D11: =Inputs!N11 | E11: =C11*D11 | F11: =SUM(Baseline!C11:G11) | G11: =SUM(Inputs!D11:H11) | H11: =E11-G11 | I11: =E11-F11 | J11: =IF(G11=0,"",E11/G11) | K11: =IF(F11=0,"",E11/F11)
A12: 3.2 | B12: RCC beams and slabs, ground to fourth floor | C12: =Inputs!C12 | D12: =Inputs!N12 | E12: =C12*D12 | F12: =SUM(Baseline!C12:G12) | G12: =SUM(Inputs!D12:H12) | H12: =E12-G12 | I12: =E12-F12 | J12: =IF(G12=0,"",E12/G12) | K12: =IF(F12=0,"",E12/F12)
A13: 3.3 | B13: Staircase and lift core RCC | C13: =Inputs!C13 | D13: =Inputs!N13 | E13: =C13*D13 | F13: =SUM(Baseline!C13:G13) | G13: =SUM(Inputs!D13:H13) | H13: =E13-G13 | I13: =E13-F13 | J13: =IF(G13=0,"",E13/G13) | K13: =IF(F13=0,"",E13/F13)
A14: 4.1 | B14: Block masonry | C14: =Inputs!C14 | D14: =Inputs!N14 | E14: =C14*D14 | F14: =SUM(Baseline!C14:G14) | G14: =SUM(Inputs!D14:H14) | H14: =E14-G14 | I14: =E14-F14 | J14: =IF(G14=0,"",E14/G14) | K14: =IF(F14=0,"",E14/F14)
A15: 4.2 | B15: Internal plaster | C15: =Inputs!C15 | D15: =Inputs!N15 | E15: =C15*D15 | F15: =SUM(Baseline!C15:G15) | G15: =SUM(Inputs!D15:H15) | H15: =E15-G15 | I15: =E15-F15 | J15: =IF(G15=0,"",E15/G15) | K15: =IF(F15=0,"",E15/F15)
A16: 4.3 | B16: External plaster and texture finish | C16: =Inputs!C16 | D16: =Inputs!N16 | E16: =C16*D16 | F16: =SUM(Baseline!C16:G16) | G16: =SUM(Inputs!D16:H16) | H16: =E16-G16 | I16: =E16-F16 | J16: =IF(G16=0,"",E16/G16) | K16: =IF(F16=0,"",E16/F16)
... A23: 6.2 | B23: Testing, commissioning and handover | C23: =Inputs!C23 | D23: =Inputs!N23 | E23: =C23*D23 | F23: =SUM(Baseline!C23:G23) | G23: =SUM(Inputs!D23:H23) | H23: =E23-G23 | I23: =E23-F23 | J23: =IF(G23=0,"",E23/G23) | K23: =IF(F23=0,"",E23/F23)
B24: PROJECT TOTAL | C24: =SUM(C5:C23) | D24: =SUM(D5:D23) | E24: =SUM(E5:E23) | F24: =SUM(F5:F23) | G24: =SUM(G5:G23) | H24: =SUM(H5:H23) | I24: =SUM(I5:I23) | J24: =E24/G24 | K24: =E24/F24

Sheet Calc P6
A1: Earned Value by Work Package — end of Period 6 (Sep-2026)
A2: EV = cumulative percent complete x budget. PV and AC are cumulative to this period.
A4: WBS ID | B4: Work Package | C4: Budget (Rs) | D4: % Complete | E4: EV (Rs) | F4: PV cum (Rs) | G4: AC cum (Rs) | H4: CV (Rs) | I4: SV (Rs) | J4: CPI | K4: SPI
A5: 1.1 | B5: Site mobilisation and enabling works | C5: =Inputs!C5 | D5: =Inputs!O5 | E5: =C5*D5 | F5: =SUM(Baseline!C5:H5) | G5: =SUM(Inputs!D5:I5) | H5: =E5-G5 | I5: =E5-F5 | J5: =IF(G5=0,"",E5/G5) | K5: =IF(F5=0,"",E5/F5)
A6: 1.2 | B6: Site office, stores and labour accommodation | C6: =Inputs!C6 | D6: =Inputs!O6 | E6: =C6*D6 | F6: =SUM(Baseline!C6:H6) | G6: =SUM(Inputs!D6:I6) | H6: =E6-G6 | I6: =E6-F6 | J6: =IF(G6=0,"",E6/G6) | K6: =IF(F6=0,"",E6/F6)
A7: 2.1 | B7: Excavation and earthwork | C7: =Inputs!C7 | D7: =Inputs!O7 | E7: =C7*D7 | F7: =SUM(Baseline!C7:H7) | G7: =SUM(Inputs!D7:I7) | H7: =E7-G7 | I7: =E7-F7 | J7: =IF(G7=0,"",E7/G7) | K7: =IF(F7=0,"",E7/F7)
A8: 2.2 | B8: PCC and footings | C8: =Inputs!C8 | D8: =Inputs!O8 | E8: =C8*D8 | F8: =SUM(Baseline!C8:H8) | G8: =SUM(Inputs!D8:I8) | H8: =E8-G8 | I8: =E8-F8 | J8: =IF(G8=0,"",E8/G8) | K8: =IF(F8=0,"",E8/F8)
A9: 2.3 | B9: Foundation RCC up to plinth | C9: =Inputs!C9 | D9: =Inputs!O9 | E9: =C9*D9 | F9: =SUM(Baseline!C9:H9) | G9: =SUM(Inputs!D9:I9) | H9: =E9-G9 | I9: =E9-F9 | J9: =IF(G9=0,"",E9/G9) | K9: =IF(F9=0,"",E9/F9)
A10: 2.4 | B10: Plinth beams and backfilling | C10: =Inputs!C10 | D10: =Inputs!O10 | E10: =C10*D10 | F10: =SUM(Baseline!C10:H10) | G10: =SUM(Inputs!D10:I10) | H10: =E10-G10 | I10: =E10-F10 | J10: =IF(G10=0,"",E10/G10) | K10: =IF(F10=0,"",E10/F10)
A11: 3.1 | B11: RCC columns, ground to fourth floor | C11: =Inputs!C11 | D11: =Inputs!O11 | E11: =C11*D11 | F11: =SUM(Baseline!C11:H11) | G11: =SUM(Inputs!D11:I11) | H11: =E11-G11 | I11: =E11-F11 | J11: =IF(G11=0,"",E11/G11) | K11: =IF(F11=0,"",E11/F11)
A12: 3.2 | B12: RCC beams and slabs, ground to fourth floor | C12: =Inputs!C12 | D12: =Inputs!O12 | E12: =C12*D12 | F12: =SUM(Baseline!C12:H12) | G12: =SUM(Inputs!D12:I12) | H12: =E12-G12 | I12: =E12-F12 | J12: =IF(G12=0,"",E12/G12) | K12: =IF(F12=0,"",E12/F12)
A13: 3.3 | B13: Staircase and lift core RCC | C13: =Inputs!C13 | D13: =Inputs!O13 | E13: =C13*D13 | F13: =SUM(Baseline!C13:H13) | G13: =SUM(Inputs!D13:I13) | H13: =E13-G13 | I13: =E13-F13 | J13: =IF(G13=0,"",E13/G13) | K13: =IF(F13=0,"",E13/F13)
A14: 4.1 | B14: Block masonry | C14: =Inputs!C14 | D14: =Inputs!O14 | E14: =C14*D14 | F14: =SUM(Baseline!C14:H14) | G14: =SUM(Inputs!D14:I14) | H14: =E14-G14 | I14: =E14-F14 | J14: =IF(G14=0,"",E14/G14) | K14: =IF(F14=0,"",E14/F14)
A15: 4.2 | B15: Internal plaster | C15: =Inputs!C15 | D15: =Inputs!O15 | E15: =C15*D15 | F15: =SUM(Baseline!C15:H15) | G15: =SUM(Inputs!D15:I15) | H15: =E15-G15 | I15: =E15-F15 | J15: =IF(G15=0,"",E15/G15) | K15: =IF(F15=0,"",E15/F15)
A16: 4.3 | B16: External plaster and texture finish | C16: =Inputs!C16 | D16: =Inputs!O16 | E16: =C16*D16 | F16: =SUM(Baseline!C16:H16) | G16: =SUM(Inputs!D16:I16) | H16: =E16-G16 | I16: =E16-F16 | J16: =IF(G16=0,"",E16/G16) | K16: =IF(F16=0,"",E16/F16)
... A23: 6.2 | B23: Testing, commissioning and handover | C23: =Inputs!C23 | D23: =Inputs!O23 | E23: =C23*D23 | F23: =SUM(Baseline!C23:H23) | G23: =SUM(Inputs!D23:I23) | H23: =E23-G23 | I23: =E23-F23 | J23: =IF(G23=0,"",E23/G23) | K23: =IF(F23=0,"",E23/F23)
B24: PROJECT TOTAL | C24: =SUM(C5:C23) | D24: =SUM(D5:D23) | E24: =SUM(E5:E23) | F24: =SUM(F5:F23) | G24: =SUM(G5:G23) | H24: =SUM(H5:H23) | I24: =SUM(I5:I23) | J24: =E24/G24 | K24: =E24/F24

Sheet Indices
A1: EVM Indices and Forecasts
A2: Every cell is a formula. Compare against the tool output in docs/04-validation-report.md.
A4: # | B4: Measure | C4: Formula as applied | D4: Period 5 | E4: Period 6 | F4: Unit
A5: 1 | B5: Budget at completion (BAC) | C5: Sum of all work package budgets | D5: =Inputs!C24 | E5: =Inputs!C24 | F5: Rs
A6: 2 | B6: Planned value (PV) | C6: Cumulative time-phased budget to date | D6: ='Calc P5'!F24 | E6: ='Calc P6'!F24 | F6: Rs
A7: 3 | B7: Earned value (EV) | C7: Sum of (% complete x budget) | D7: ='Calc P5'!E24 | E7: ='Calc P6'!E24 | F7: Rs
A8: 4 | B8: Actual cost (AC) | C8: Cumulative cost booked to date | D8: ='Calc P5'!G24 | E8: ='Calc P6'!G24 | F8: Rs
A9: 5 | B9: Cost variance (CV) | C9: EV - AC | D9: ='Calc P5'!E24-'Calc P5'!G24 | E9: ='Calc P6'!E24-'Calc P6'!G24 | F9: Rs
A10: 6 | B10: Schedule variance (SV) | C10: EV - PV | D10: ='Calc P5'!E24-'Calc P5'!F24 | E10: ='Calc P6'!E24-'Calc P6'!F24 | F10: Rs
A11: 7 | B11: Cost variance % | C11: CV / EV | D11: =('Calc P5'!E24-'Calc P5'!G24)/'Calc P5'!E24 | E11: =('Calc P6'!E24-'Calc P6'!G24)/'Calc P6'!E24 | F11: %
A12: 8 | B12: Schedule variance % | C12: SV / PV | D12: =('Calc P5'!E24-'Calc P5'!F24)/'Calc P5'!F24 | E12: =('Calc P6'!E24-'Calc P6'!F24)/'Calc P6'!F24 | F12: %
A13: 9 | B13: Cost performance index (CPI) | C13: EV / AC | D13: ='Calc P5'!E24/'Calc P5'!G24 | E13: ='Calc P6'!E24/'Calc P6'!G24 | F13: ratio
A14: 10 | B14: Schedule performance index (SPI) | C14: EV / PV | D14: ='Calc P5'!E24/'Calc P5'!F24 | E14: ='Calc P6'!E24/'Calc P6'!F24 | F14: ratio
A15: 11 | B15: Percent complete | C15: EV / BAC | D15: ='Calc P5'!E24/Inputs!C24 | E15: ='Calc P6'!E24/Inputs!C24 | F15: %
A16: 12 | B16: Percent spent | C16: AC / BAC | D16: ='Calc P5'!G24/Inputs!C24 | E16: ='Calc P6'!G24/Inputs!C24 | F16: %
A17: 13 | B17: Percent scheduled | C17: PV / BAC | D17: ='Calc P5'!F24/Inputs!C24 | E17: ='Calc P6'!F24/Inputs!C24 | F17: %
A18: 14 | B18: Earned schedule (ES) | C18: Baseline time at which PV equals current EV | D18: =IFERROR(MATCH('Calc P5'!E24,Baseline!$C$26:$N$26,1)+('Calc P5'!E24-INDEX(Baseline!$C$26:$N$26,MATCH('Calc P5'!E24,Baseline!$C$26:$N$26,1)))/(INDEX(Baseline!$C$26:$N$26,MATCH('Calc P5'!E24,Baseline!$C$26:$N$26,1)+1)-INDEX(Baseline!$C$26:$N$26,MATCH('Calc P5'!E24,Baseline!$C$26:$N$26,1))),'Calc P5'!E24/INDEX(Baseline!$C$26:$N$26,1)) | E18: =IFERROR(MATCH('Calc P6'!E24,Baseline!$C$26:$N$26,1)+('Calc P6'!E24-INDEX(Baseline!$C$26:$N$26,MATCH('Calc P6'!E24,Baseline!$C$26:$N$26,1)))/(INDEX(Baseline!$C$26:$N$26,MATCH('Calc P6'!E24,Baseline!$C$26:$N$26,1)+1)-INDEX(Baseline!$C$26:$N$26,MATCH('Calc P6'!E24,Baseline!$C$26:$N$26,1))),'Calc P6'!E24/INDEX(Baseline!$C$26:$N$26,1)) | F18: periods
A19: 15 | B19: Actual time (AT) | C19: Periods elapsed at the data date | D19: =5 | E19: =6 | F19: periods
A20: 16 | B20: Schedule variance, time SV(t) | C20: ES - AT | D20: =IFERROR(MATCH('Calc P5'!E24,Baseline!$C$26:$N$26,1)+('Calc P5'!E24-INDEX(Baseline!$C$26:$N$26,MATCH('Calc P5'!E24,Baseline!$C$26:$N$26,1)))/(INDEX(Baseline!$C$26:$N$26,MATCH('Calc P5'!E24,Baseline!$C$26:$N$26,1)+1)-INDEX(Baseline!$C$26:$N$26,MATCH('Calc P5'!E24,Baseline!$C$26:$N$26,1))),'Calc P5'!E24/INDEX(Baseline!$C$26:$N$26,1))-5 | E20: =IFERROR(MATCH('Calc P6'!E24,Baseline!$C$26:$N$26,1)+('Calc P6'!E24-INDEX(Baseline!$C$26:$N$26,MATCH('Calc P6'!E24,Baseline!$C$26:$N$26,1)))/(INDEX(Baseline!$C$26:$N$26,MATCH('Calc P6'!E24,Baseline!$C$26:$N$26,1)+1)-INDEX(Baseline!$C$26:$N$26,MATCH('Calc P6'!E24,Baseline!$C$26:$N$26,1))),'Calc P6'!E24/INDEX(Baseline!$C$26:$N$26,1))-6 | F20: periods
A21: 17 | B21: Schedule performance index SPI(t) | C21: ES / AT | D21: =(IFERROR(MATCH('Calc P5'!E24,Baseline!$C$26:$N$26,1)+('Calc P5'!E24-INDEX(Baseline!$C$26:$N$26,MATCH('Calc P5'!E24,Baseline!$C$26:$N$26,1)))/(INDEX(Baseline!$C$26:$N$26,MATCH('Calc P5'!E24,Baseline!$C$26:$N$26,1)+1)-INDEX(Baseline!$C$26:$N$26,MATCH('Calc P5'!E24,Baseline!$C$26:$N$26,1))),'Calc P5'!E24/INDEX(Baseline!$C$26:$N$26,1)))/5 | E21: =(IFERROR(MATCH('Calc P6'!E24,Baseline!$C$26:$N$26,1)+('Calc P6'!E24-INDEX(Baseline!$C$26:$N$26,MATCH('Calc P6'!E24,Baseline!$C$26:$N$26,1)))/(INDEX(Baseline!$C$26:$N$26,MATCH('Calc P6'!E24,Baseline!$C$26:$N$26,1)+1)-INDEX(Baseline!$C$26:$N$26,MATCH('Calc P6'!E24,Baseline!$C$26:$N$26,1))),'Calc P6'!E24/INDEX(Baseline!$C$26:$N$26,1)))/6 | F21: ratio
A22: 18 | B22: EAC method 1 | C22: BAC / CPI | D22: =Inputs!C24/('Calc P5'!E24/'Calc P5'!G24) | E22: =Inputs!C24/('Calc P6'!E24/'Calc P6'!G24) | F22: Rs
A23: 19 | B23: EAC method 2 | C23: AC + (BAC - EV) | D23: ='Calc P5'!G24+(Inputs!C24-'Calc P5'!E24) | E23: ='Calc P6'!G24+(Inputs!C24-'Calc P6'!E24) | F23: Rs
A24: 20 | B24: EAC method 3 | C24: AC + (BAC - EV) / (CPI x SPI) | D24: ='Calc P5'!G24+(Inputs!C24-'Calc P5'!E24)/(('Calc P5'!E24/'Calc P5'!G24)*('Calc P5'!E24/'Calc P5'!F24)) | E24: ='Calc P6'!G24+(Inputs!C24-'Calc P6'!E24)/(('Calc P6'!E24/'Calc P6'!G24)*('Calc P6'!E24/'Calc P6'!F24)) | F24: Rs
A25: 21 | B25: EAC method 4 | C25: AC + (BAC - EV) / (0.8 CPI + 0.2 SPI) | D25: ='Calc P5'!G24+(Inputs!C24-'Calc P5'!E24)/(0.8*('Calc P5'!E24/'Calc P5'!G24)+0.2*('Calc P5'!E24/'Calc P5'!F24)) | E25: ='Calc P6'!G24+(Inputs!C24-'Calc P6'!E24)/(0.8*('Calc P6'!E24/'Calc P6'!G24)+0.2*('Calc P6'!E24/'Calc P6'!F24)) | F25: Rs
A26: 22 | B26: ETC (on EAC method 1) | C26: EAC1 - AC | D26: =Inputs!C24/('Calc P5'!E24/'Calc P5'!G24)-'Calc P5'!G24 | E26: =Inputs!C24/('Calc P6'!E24/'Calc P6'!G24)-'Calc P6'!G24 | F26: Rs
A27: 23 | B27: VAC (on EAC method 1) | C27: BAC - EAC1 | D27: =Inputs!C24-Inputs!C24/('Calc P5'!E24/'Calc P5'!G24) | E27: =Inputs!C24-Inputs!C24/('Calc P6'!E24/'Calc P6'!G24) | F27: Rs
A28: 24 | B28: TCPI to BAC | C28: (BAC - EV) / (BAC - AC) | D28: =(Inputs!C24-'Calc P5'!E24)/(Inputs!C24-'Calc P5'!G24) | E28: =(Inputs!C24-'Calc P6'!E24)/(Inputs!C24-'Calc P6'!G24) | F28: ratio
A29: 25 | B29: TCPI to EAC1 | C29: (BAC - EV) / (EAC1 - AC) | D29: =(Inputs!C24-'Calc P5'!E24)/(Inputs!C24/('Calc P5'!E24/'Calc P5'!G24)-'Calc P5'!G24) | E29: =(Inputs!C24-'Calc P6'!E24)/(Inputs!C24/('Calc P6'!E24/'Calc P6'!G24)-'Calc P6'!G24) | F29: ratio
B31: Notes
B32: 1. Rounding is applied by the cell number format only. No value is rounded in the calculation chain; rounding an intermediate index moves EAC method 3 by tens of rupees.
B33: 2. Earned Schedule assumes planned value accrues linearly within a period. Over a monthly period on building work this is a mild assumption.
B34: 3. TCPI to EAC1 must equal CPI exactly. It is an algebraic identity and a check that the forecast chain is intact.
B35: 4. EAC method 2 implies VAC equal to the cost variance already incurred. Also an identity.
