Workbook

Sheet Dashboard
A1: Academic Block (G+4 RCC) - Institutional Campus
A2: CE725-CASE-01 | data date: end of Period 6 (Sep-2026)
B4: POSITION
B5: Budget at completion (BAC) | C5: =Inputs!$C$24
B6: Planned value (PV) | C6: =EVM!C10
B7: Earned value (EV) | C7: =EVM!D10
B8: Actual cost (AC) | C8: =EVM!E10
B9: Percent complete | C9: =EVM!J10
B10: Percent spent | C10: =EVM!K10
B11: VARIANCE
B13: Cost variance (CV) | C13: =EVM!F10
B14: Schedule variance (SV) | C14: =EVM!G10
B15: Cost performance index (CPI) | C15: =EVM!H10 | D15: Rupees of budgeted work per rupee spent. Below 1.00 is overspending.
B16: Schedule performance index (SPI) | C16: =EVM!I10 | D16: Work done per unit of work scheduled. Below 1.00 is behind.
B17: FORECAST
B19: EAC — performance continues | C19: =Inputs!$C$24/EVM!H10 | D19: BAC / CPI. The default forecast.
B20: EAC — variance was a one-off | C20: =EVM!E10+(Inputs!$C$24-EVM!D10) | D20: AC + (BAC - EV). The most optimistic assumption available.
B21: EAC — cost and schedule pressure | C21: =EVM!E10+(Inputs!$C$24-EVM!D10)/(EVM!H10*EVM!I10) | D21: AC + (BAC - EV) / (CPI x SPI). Recovering schedule normally costs money.
B22: ETC (on EAC, performance continues) | C22: =Inputs!$C$24/EVM!H10-EVM!E10
B23: VAC (on EAC, performance continues) | C23: =Inputs!$C$24-Inputs!$C$24/EVM!H10
B24: TCPI to finish on budget | C24: =(Inputs!$C$24-EVM!D10)/(Inputs!$C$24-EVM!E10) | D24: Efficiency the REMAINING work must achieve. Compare it with CPI.
B26: VERDICT | C26: =IF(AND(EVM!H10>=0.95,EVM!I10>=0.95),"ON TRACK",IF(AND(EVM!H10<0.95,EVM!I10<0.95),"BEHIND SCHEDULE AND OVERSPENT",IF(EVM!H10<0.95,"OVERSPENT","BEHIND SCHEDULE"))) | D26: Thresholds: an index within 5% of plan is treated as noise.

Sheet Inputs
A1: Academic Block (G+4 RCC) - Institutional Campus — EVM Inputs
A2: Yellow cells are editable. Change any of them and every index, forecast and chart in this workbook recalculates.
A4: WBS ID | B4: Work Package | C4: Budget (Rs) | D4: AC P1 | E4: AC P2 | F4: AC P3 | G4: AC P4 | H4: AC P5 | I4: AC P6 | J4: %C P1 | K4: %C P2 | L4: %C P3 | M4: %C P4 | N4: %C P5 | O4: %C P6
A5: 1.1 | B5: Site mobilisation and enabling works | C5: 2500000 | D5: 1500000 | E5: 1200000 | F5: 0 | G5: 0 | H5: 0 | I5: 0 | J5: 0.55 | K5: 1 | L5: 1 | M5: 1 | N5: 1 | O5: 1
A6: 1.2 | B6: Site office, stores and labour accommodation | C6: 1800000 | D6: 950000 | E6: 900000 | F6: 0 | G6: 0 | H6: 0 | I6: 0 | J6: 0.5 | K6: 1 | L6: 1 | M6: 1 | N6: 1 | O6: 1
A7: 2.1 | B7: Excavation and earthwork | C7: 4200000 | D7: 1100000 | E7: 1500000 | F7: 1650000 | G7: 1100000 | H7: 750000 | I7: 0 | J7: 0.2 | K7: 0.45 | L7: 0.72 | M7: 0.9 | N7: 1 | O7: 1
A8: 2.2 | B8: PCC and footings | C8: 6800000 | D8: 0 | E8: 1100000 | F8: 1950000 | G8: 2500000 | H8: 1850000 | I8: 0 | J8: 0 | K8: 0.15 | L8: 0.42 | M8: 0.78 | N8: 1 | O8: 1
A9: 2.3 | B9: Foundation RCC up to plinth | C9: 9500000 | D9: 0 | E9: 0 | F9: 1900000 | G9: 3000000 | H9: 3400000 | I9: 2500000 | J9: 0 | K9: 0 | L9: 0.18 | M9: 0.46 | N9: 0.8 | O9: 1
A10: 2.4 | B10: Plinth beams and backfilling | C10: 3800000 | D10: 0 | E10: 0 | F10: 0 | G10: 850000 | H10: 1600000 | I10: 1650000 | J10: 0 | K10: 0 | L10: 0 | M10: 0.2 | N10: 0.62 | O10: 1
A11: 3.1 | B11: RCC columns, ground to fourth floor | C11: 14500000 | D11: 0 | E11: 0 | F11: 0 | G11: 0 | H11: 1300000 | I11: 2300000 | J11: 0 | K11: 0 | L11: 0 | M11: 0 | N11: 0.08 | O11: 0.22
A12: 3.2 | B12: RCC beams and slabs, ground to fourth floor | C12: 21000000 | D12: 0 | E12: 0 | F12: 0 | G12: 0 | H12: 1200000 | I12: 2100000 | J12: 0 | K12: 0 | L12: 0 | M12: 0 | N12: 0.05 | O12: 0.14
A13: 3.3 | B13: Staircase and lift core RCC | C13: 5500000 | D13: 0 | E13: 0 | F13: 0 | G13: 0 | H13: 0 | I13: 0 | J13: 0 | K13: 0 | L13: 0 | M13: 0 | N13: 0 | O13: 0
A14: 4.1 | B14: Block masonry | C14: 8800000 | D14: 0 | E14: 0 | F14: 0 | G14: 0 | H14: 0 | I14: 0 | J14: 0 | K14: 0 | L14: 0 | M14: 0 | N14: 0 | O14: 0
A15: 4.2 | B15: Internal plaster | C15: 5200000 | D15: 0 | E15: 0 | F15: 0 | G15: 0 | H15: 0 | I15: 0 | J15: 0 | K15: 0 | L15: 0 | M15: 0 | N15: 0 | O15: 0
A16: 4.3 | B16: External plaster and texture finish | C16: 4600000 | D16: 0 | E16: 0 | F16: 0 | G16: 0 | H16: 0 | I16: 0 | J16: 0 | K16: 0 | L16: 0 | M16: 0 | N16: 0 | O16: 0
... A23: 6.2 | B23: Testing, commissioning and handover | C23: 2800000 | D23: 0 | E23: 0 | F23: 0 | G23: 0 | H23: 0 | I23: 0 | J23: 0 | K23: 0 | L23: 0 | M23: 0 | N23: 0 | O23: 0
B24: TOTAL | C24: =SUM(C5:C23) | D24: =SUM(D5:D23) | E24: =SUM(E5:E23) | F24: =SUM(F5:F23) | G24: =SUM(G5:G23) | H24: =SUM(H5:H23) | I24: =SUM(I5:I23)

Sheet Baseline
A1: Time-Phased Budget (Planned Value)
A4: WBS ID | B4: Work Package | C4: P1 | D4: P2 | E4: P3 | F4: P4 | G4: P5 | H4: P6 | I4: P7 | J4: P8 | K4: P9 | L4: P10 | M4: P11 | N4: P12
A5: 1.1 | B5: Site mobilisation and enabling works | C5: 1250000 | D5: 1250000 | E5: 0 | F5: 0 | G5: 0 | H5: 0 | I5: 0 | J5: 0 | K5: 0 | L5: 0 | M5: 0 | N5: 0
A6: 1.2 | B6: Site office, stores and labour accommodation | C6: 900000 | D6: 900000 | E6: 0 | F6: 0 | G6: 0 | H6: 0 | I6: 0 | J6: 0 | K6: 0 | L6: 0 | M6: 0 | N6: 0
A7: 2.1 | B7: Excavation and earthwork | C7: 1400000 | D7: 1400000 | E7: 1400000 | F7: 0 | G7: 0 | H7: 0 | I7: 0 | J7: 0 | K7: 0 | L7: 0 | M7: 0 | N7: 0
A8: 2.2 | B8: PCC and footings | C8: 0 | D8: 1762963 | E8: 3274074.1 | F8: 1762963 | G8: 0 | H8: 0 | I8: 0 | J8: 0 | K8: 0 | L8: 0 | M8: 0 | N8: 0
A9: 2.3 | B9: Foundation RCC up to plinth | C9: 0 | D9: 0 | E9: 2462963 | F9: 4574074.1 | G9: 2462963 | H9: 0 | I9: 0 | J9: 0 | K9: 0 | L9: 0 | M9: 0 | N9: 0
A10: 2.4 | B10: Plinth beams and backfilling | C10: 0 | D10: 0 | E10: 0 | F10: 1900000 | G10: 1900000 | H10: 0 | I10: 0 | J10: 0 | K10: 0 | L10: 0 | M10: 0 | N10: 0
A11: 3.1 | B11: RCC columns, ground to fourth floor | C11: 0 | D11: 0 | E11: 0 | F11: 0 | G11: 1508000 | H11: 3596000 | I11: 4292000 | J11: 3596000 | K11: 1508000 | L11: 0 | M11: 0 | N11: 0
A12: 3.2 | B12: RCC beams and slabs, ground to fourth floor | C12: 0 | D12: 0 | E12: 0 | F12: 0 | G12: 1555555.6 | H12: 3888888.9 | I12: 5055555.6 | J12: 5055555.6 | K12: 3888888.9 | L12: 1555555.6 | M12: 0 | N12: 0
A13: 3.3 | B13: Staircase and lift core RCC | C13: 0 | D13: 0 | E13: 0 | F13: 0 | G13: 0 | H13: 1100000 | I13: 1100000 | J13: 1100000 | K13: 1100000 | L13: 1100000 | M13: 0 | N13: 0
A14: 4.1 | B14: Block masonry | C14: 0 | D14: 0 | E14: 0 | F14: 0 | G14: 0 | H14: 0 | I14: 915200 | J14: 2182400 | K14: 2604800 | L14: 2182400 | M14: 915200 | N14: 0
A15: 4.2 | B15: Internal plaster | C15: 0 | D15: 0 | E15: 0 | F15: 0 | G15: 0 | H15: 0 | I15: 0 | J15: 0 | K15: 812500 | L15: 1787500 | M15: 1787500 | N15: 812500
A16: 4.3 | B16: External plaster and texture finish | C16: 0 | D16: 0 | E16: 0 | F16: 0 | G16: 0 | H16: 0 | I16: 0 | J16: 0 | K16: 1150000 | L16: 1150000 | M16: 1150000 | N16: 1150000
... A23: 6.2 | B23: Testing, commissioning and handover | C23: 0 | D23: 0 | E23: 0 | F23: 0 | G23: 0 | H23: 0 | I23: 0 | J23: 0 | K23: 0 | L23: 0 | M23: 0 | N23: 2800000
B24: TOTAL | C24: =SUM(C5:C23) | D24: =SUM(D5:D23) | E24: =SUM(E5:E23) | F24: =SUM(F5:F23) | G24: =SUM(G5:G23) | H24: =SUM(H5:H23) | I24: =SUM(I5:I23) | J24: =SUM(J5:J23) | ... N24: =SUM(N5:N23)

Sheet EVM
A1: Earned Value by Reporting Period
A2: Data date: end of Period 6. EV and AC stop there; beyond it they return NA() so the charts break the line rather than plotting zero.
A4: Period | B4: Label | C4: PV cum | D4: EV cum | E4: AC cum | F4: CV | G4: SV | H4: CPI | I4: SPI | J4: % complete | K4: % spent
A5: 1 | B5: Apr-2026 | C5: =SUM(Baseline!$C$5:C$23) | D5: =SUMPRODUCT(Inputs!$C$5:$C$23,Inputs!J$5:J$23) | E5: =SUM(Inputs!$D$5:D$23) | F5: =IF(ISNA(D5),NA(),D5-E5) | G5: =IF(ISNA(D5),NA(),D5-C5) | H5: =IF(ISNA(D5),NA(),IF(E5=0,NA(),D5/E5)) | I5: =IF(ISNA(D5),NA(),IF(C5=0,NA(),D5/C5)) | J5: =IF(ISNA(D5),NA(),D5/Inputs!$C$24) | K5: =IF(ISNA(E5),NA(),E5/Inputs!$C$24)
A6: 2 | B6: May-2026 | C6: =SUM(Baseline!$C$5:D$23) | D6: =SUMPRODUCT(Inputs!$C$5:$C$23,Inputs!K$5:K$23) | E6: =SUM(Inputs!$D$5:E$23) | F6: =IF(ISNA(D6),NA(),D6-E6) | G6: =IF(ISNA(D6),NA(),D6-C6) | H6: =IF(ISNA(D6),NA(),IF(E6=0,NA(),D6/E6)) | I6: =IF(ISNA(D6),NA(),IF(C6=0,NA(),D6/C6)) | J6: =IF(ISNA(D6),NA(),D6/Inputs!$C$24) | K6: =IF(ISNA(E6),NA(),E6/Inputs!$C$24)
A7: 3 | B7: Jun-2026 | C7: =SUM(Baseline!$C$5:E$23) | D7: =SUMPRODUCT(Inputs!$C$5:$C$23,Inputs!L$5:L$23) | E7: =SUM(Inputs!$D$5:F$23) | F7: =IF(ISNA(D7),NA(),D7-E7) | G7: =IF(ISNA(D7),NA(),D7-C7) | H7: =IF(ISNA(D7),NA(),IF(E7=0,NA(),D7/E7)) | I7: =IF(ISNA(D7),NA(),IF(C7=0,NA(),D7/C7)) | J7: =IF(ISNA(D7),NA(),D7/Inputs!$C$24) | K7: =IF(ISNA(E7),NA(),E7/Inputs!$C$24)
A8: 4 | B8: Jul-2026 | C8: =SUM(Baseline!$C$5:F$23) | D8: =SUMPRODUCT(Inputs!$C$5:$C$23,Inputs!M$5:M$23) | E8: =SUM(Inputs!$D$5:G$23) | F8: =IF(ISNA(D8),NA(),D8-E8) | G8: =IF(ISNA(D8),NA(),D8-C8) | H8: =IF(ISNA(D8),NA(),IF(E8=0,NA(),D8/E8)) | I8: =IF(ISNA(D8),NA(),IF(C8=0,NA(),D8/C8)) | J8: =IF(ISNA(D8),NA(),D8/Inputs!$C$24) | K8: =IF(ISNA(E8),NA(),E8/Inputs!$C$24)
A9: 5 | B9: Aug-2026 | C9: =SUM(Baseline!$C$5:G$23) | D9: =SUMPRODUCT(Inputs!$C$5:$C$23,Inputs!N$5:N$23) | E9: =SUM(Inputs!$D$5:H$23) | F9: =IF(ISNA(D9),NA(),D9-E9) | G9: =IF(ISNA(D9),NA(),D9-C9) | H9: =IF(ISNA(D9),NA(),IF(E9=0,NA(),D9/E9)) | I9: =IF(ISNA(D9),NA(),IF(C9=0,NA(),D9/C9)) | J9: =IF(ISNA(D9),NA(),D9/Inputs!$C$24) | K9: =IF(ISNA(E9),NA(),E9/Inputs!$C$24)
A10: 6 | B10: Sep-2026 | C10: =SUM(Baseline!$C$5:H$23) | D10: =SUMPRODUCT(Inputs!$C$5:$C$23,Inputs!O$5:O$23) | E10: =SUM(Inputs!$D$5:I$23) | F10: =IF(ISNA(D10),NA(),D10-E10) | G10: =IF(ISNA(D10),NA(),D10-C10) | H10: =IF(ISNA(D10),NA(),IF(E10=0,NA(),D10/E10)) | I10: =IF(ISNA(D10),NA(),IF(C10=0,NA(),D10/C10)) | J10: =IF(ISNA(D10),NA(),D10/Inputs!$C$24) | K10: =IF(ISNA(E10),NA(),E10/Inputs!$C$24)
A11: 7 | B11: Oct-2026 | C11: =SUM(Baseline!$C$5:I$23) | D11: =NA() | E11: =NA() | F11: =IF(ISNA(D11),NA(),D11-E11) | G11: =IF(ISNA(D11),NA(),D11-C11) | H11: =IF(ISNA(D11),NA(),IF(E11=0,NA(),D11/E11)) | I11: =IF(ISNA(D11),NA(),IF(C11=0,NA(),D11/C11)) | J11: =IF(ISNA(D11),NA(),D11/Inputs!$C$24) | K11: =IF(ISNA(E11),NA(),E11/Inputs!$C$24)
A12: 8 | B12: Nov-2026 | C12: =SUM(Baseline!$C$5:J$23) | D12: =NA() | E12: =NA() | F12: =IF(ISNA(D12),NA(),D12-E12) | G12: =IF(ISNA(D12),NA(),D12-C12) | H12: =IF(ISNA(D12),NA(),IF(E12=0,NA(),D12/E12)) | I12: =IF(ISNA(D12),NA(),IF(C12=0,NA(),D12/C12)) | J12: =IF(ISNA(D12),NA(),D12/Inputs!$C$24) | K12: =IF(ISNA(E12),NA(),E12/Inputs!$C$24)
A13: 9 | B13: Dec-2026 | C13: =SUM(Baseline!$C$5:K$23) | D13: =NA() | E13: =NA() | F13: =IF(ISNA(D13),NA(),D13-E13) | G13: =IF(ISNA(D13),NA(),D13-C13) | H13: =IF(ISNA(D13),NA(),IF(E13=0,NA(),D13/E13)) | I13: =IF(ISNA(D13),NA(),IF(C13=0,NA(),D13/C13)) | J13: =IF(ISNA(D13),NA(),D13/Inputs!$C$24) | K13: =IF(ISNA(E13),NA(),E13/Inputs!$C$24)
A14: 10 | B14: Jan-2027 | C14: =SUM(Baseline!$C$5:L$23) | D14: =NA() | E14: =NA() | F14: =IF(ISNA(D14),NA(),D14-E14) | G14: =IF(ISNA(D14),NA(),D14-C14) | H14: =IF(ISNA(D14),NA(),IF(E14=0,NA(),D14/E14)) | I14: =IF(ISNA(D14),NA(),IF(C14=0,NA(),D14/C14)) | J14: =IF(ISNA(D14),NA(),D14/Inputs!$C$24) | K14: =IF(ISNA(E14),NA(),E14/Inputs!$C$24)
A15: 11 | B15: Feb-2027 | C15: =SUM(Baseline!$C$5:M$23) | D15: =NA() | E15: =NA() | F15: =IF(ISNA(D15),NA(),D15-E15) | G15: =IF(ISNA(D15),NA(),D15-C15) | H15: =IF(ISNA(D15),NA(),IF(E15=0,NA(),D15/E15)) | I15: =IF(ISNA(D15),NA(),IF(C15=0,NA(),D15/C15)) | J15: =IF(ISNA(D15),NA(),D15/Inputs!$C$24) | K15: =IF(ISNA(E15),NA(),E15/Inputs!$C$24)
A16: 12 | B16: Mar-2027 | C16: =SUM(Baseline!$C$5:N$23) | D16: =NA() | E16: =NA() | F16: =IF(ISNA(D16),NA(),D16-E16) | G16: =IF(ISNA(D16),NA(),D16-C16) | H16: =IF(ISNA(D16),NA(),IF(E16=0,NA(),D16/E16)) | I16: =IF(ISNA(D16),NA(),IF(C16=0,NA(),D16/C16)) | J16: =IF(ISNA(D16),NA(),D16/Inputs!$C$24) | K16: =IF(ISNA(E16),NA(),E16/Inputs!$C$24)

Sheet Variance
A1: Cost and Schedule Variance by Work Package — Period 6
A2: Where the project variance actually is. Only packages that have started.
A4: WBS ID | B4: Work Package | C4: Budget | D4: EV | E4: AC | F4: CV | G4: CPI | H4: % complete
A5: 2.1 | B5: Excavation and earthwork | C5: 4200000 | D5: 4200000 | E5: 6100000 | F5: -1900000 | G5: 0.68852459 | H5: 1
A6: 2.3 | B6: Foundation RCC up to plinth | C6: 9500000 | D6: 9500000 | E6: 10800000 | F6: -1300000 | G6: 0.87962963 | H6: 1
A7: 2.2 | B7: PCC and footings | C7: 6800000 | D7: 6800000 | E7: 7400000 | F7: -600000 | G7: 0.91891892 | H7: 1
A8: 3.1 | B8: RCC columns, ground to fourth floor | C8: 14500000 | D8: 3190000 | E8: 3600000 | F8: -410000 | G8: 0.88611111 | H8: 0.22
A9: 3.2 | B9: RCC beams and slabs, ground to fourth floor | C9: 21000000 | D9: 2940000 | E9: 3300000 | F9: -360000 | G9: 0.89090909 | H9: 0.14
A10: 2.4 | B10: Plinth beams and backfilling | C10: 3800000 | D10: 3800000 | E10: 4100000 | F10: -300000 | G10: 0.92682927 | H10: 1
A11: 1.1 | B11: Site mobilisation and enabling works | C11: 2500000 | D11: 2500000 | E11: 2700000 | F11: -200000 | G11: 0.92592593 | H11: 1
A12: 1.2 | B12: Site office, stores and labour accommodation | C12: 1800000 | D12: 1800000 | E12: 1850000 | F12: -50000 | G12: 0.97297297 | H12: 1

Sheet Read Me
A1: About this workbook
A3: Exported from the CE725 EVM Dashboard for Academic Block (G+4 RCC) - Institutional Campus.
A4: Data date: end of Period 6 (Sep-2026).
A6: LIVE, NOT A SNAPSHOT
A8: Every figure on the Dashboard and EVM sheets is an Excel formula. Edit any
A9: yellow cell on Inputs or Baseline and the whole workbook recalculates. That
A10: is the point: the numbers can be interrogated and re-run without the tool.
A12: WHAT TO EDIT
A14: Inputs budgets, actual cost per period, percent complete per period
A15: Baseline the time-phased budget
A17: Nothing else is meant to be typed into.
A19: LIMITATIONS
... A35: recomputes them from the inputs and is what should be read.
